process_life_and_death_monitor
